mcp_server_git/__init__.py
mcp_server_git/__main__.py
mcp_server_git/server.py
chungoid_mcp_server_git-0.6.2.dev3.dist-info/METADATA
chungoid_mcp_server_git-0.6.2.dev3.dist-info/WHEEL
chungoid_mcp_server_git-0.6.2.dev3.dist-info/entry_points.txt
chungoid_mcp_server_git-0.6.2.dev3.dist-info/licenses/LICENSE
chungoid_mcp_server_git-0.6.2.dev3.dist-info/RECORD
