Metadata-Version: 2.4
Name: chungoid-mcp-server-git
Version: 0.6.2.dev3
Summary: A Model Context Protocol server providing tools for interacting with git repositories via the command line
Author: Anthropic, PBC.
Maintainer-email: David Soria Parra <davidsp@anthropic.com>
License: MIT
License-File: LICENSE
Keywords: automation,git,llm,mcp
Classifier: Development Status :: 4 - Beta
Classifier: Intended Audience :: Developers
Classifier: License :: OSI Approved :: MIT License
Classifier: Programming Language :: Python :: 3
Classifier: Programming Language :: Python :: 3.10
Requires-Python: >=3.10
Requires-Dist: click>=8.1.7
Requires-Dist: gitpython>=3.1.43
Requires-Dist: mcp>=1.0.0
Requires-Dist: pydantic>=2.0.0
